curlifier/__init__.py
curlifier/__version__.py
curlifier/api.py
curlifier/builders/__init__.py
curlifier/builders/base.py
curlifier/builders/configurator.py
curlifier/builders/curl.py
curlifier/builders/exceptions.py
curlifier/builders/transmitter.py
curlifier/py.typed
curlifier/structures/__init__.py
curlifier/structures/commands.py
curlifier/structures/http_methods.py
curlifier-1.0.4.dist-info/LICENSE
curlifier-1.0.4.dist-info/METADATA
curlifier-1.0.4.dist-info/WHEEL
curlifier-1.0.4.dist-info/RECORD
