Metadata-Version: 2.3
Name: curlifier
Version: 1.0.4
Summary: Converts Request objects to curl string
License: MIT
Keywords: curl,curlify,to-curl,requests,request-converter
Author: Timur Valiev
Author-email: cptchunk@yandex.ru
Requires-Python: >=3.10,<4.0
Classifier: Development Status :: 5 - Production/Stable
Classifier: Intended Audience :: Developers
Classifier: License :: OSI Approved :: MIT License
Classifier: Programming Language :: Python :: 3
Classifier: Programming Language :: Python :: 3.10
Classifier: Programming Language :: Python :: 3.11
Classifier: Programming Language :: Python :: 3.12
Classifier: Programming Language :: Python :: 3.13
Classifier: Programming Language :: Python :: 3.14
Classifier: Topic :: Software Development :: Libraries :: Python Modules
Classifier: Typing :: Typed
Requires-Dist: requests (>=2.0,<3.0)
Project-URL: Homepage, https://github.com/imtoopunkforyou/curlifier
